datawhys_dashboard/__init__.py
datawhys_dashboard/_dashboards.py
datawhys_dashboard/api/__init__.py
datawhys_dashboard/api/_base.py
datawhys_dashboard/api/_portals.py
datawhys_dashboard-0.1.2.dist-info/WHEEL
datawhys_dashboard-0.1.2.dist-info/METADATA
datawhys_dashboard-0.1.2.dist-info/RECORD
