Metadata-Version: 2.1
Name: datawhys-dashboard
Version: 0.1.2
Summary: DataWhys Dashboard SDK allows users to create a DataWhys Dashboard directly within their Python notebooks
Home-page: https://datawhys.ai
Keywords: datawhys,dashboard,data,visualization
Author: DataWhys DevTeam
Author-email: devteam@datawhys.ai
Requires-Python: >=3.6.2,<4.0.0
Classifier: Development Status :: 3 - Alpha
Classifier: Intended Audience :: Developers
Classifier: Natural Language :: English
Classifier: Programming Language :: Python :: 3
Classifier: Programming Language :: Python :: 3.10
Classifier: Programming Language :: Python :: 3.7
Classifier: Programming Language :: Python :: 3.8
Classifier: Programming Language :: Python :: 3.9
Classifier: Topic :: Scientific/Engineering
Classifier: Topic :: Scientific/Engineering :: Artificial Intelligence
Classifier: Topic :: Scientific/Engineering :: Visualization
Classifier: Topic :: Software Development
Requires-Dist: pandas (>=1.1.5,<2.0.0)
Requires-Dist: requests (>=2.27.0,<3.0.0)
Project-URL: Repository, https://bitbucket.org/mondobrain/datawhys-dashboard-sdk
